statreg/__init__.py
statreg/basis.py
statreg/memoize.py
statreg/vector.py
statreg/examples/__init__.py
statreg/examples/function.py
statreg/examples/kernels.py
statreg/model/__init__.py
statreg/model/gauss_error.py
statreg-0.0.1.dev1.dist-info/AUTHORS.TXT
statreg-0.0.1.dev1.dist-info/LICENSE
statreg-0.0.1.dev1.dist-info/METADATA
statreg-0.0.1.dev1.dist-info/WHEEL
statreg-0.0.1.dev1.dist-info/top_level.txt
statreg-0.0.1.dev1.dist-info/RECORD
